README.rst
setup.py
semantic_web_pygments/__init__.py
semantic_web_pygments/lexer.py
semantic_web_pygments.egg-info/PKG-INFO
semantic_web_pygments.egg-info/SOURCES.txt
semantic_web_pygments.egg-info/dependency_links.txt
semantic_web_pygments.egg-info/entry_points.txt
semantic_web_pygments.egg-info/requires.txt
semantic_web_pygments.egg-info/top_level.txt